<?xml version="1.0" encoding="UTF-8"?>
<con:soapui-project id="28a059c6-0aeb-42e2-a980-4b37c0bfd2b4" created="3.53.0" activeEnvironment="Default environment" encryptionMode="Not encrypted" name="Activity3" projectVersion="" updated="3.54.0 2024-07-17T11:22:49Z" xmlns:con="http://eviware.com/soapui/config">
  <con:settings/>
  <con:interface xsi:type="con:WsdlInterface" id="c91d569d-e4cc-497f-806e-b8713ff0952b" wsaVersion="NONE" name="CalculatorSoap12" type="wsdl" bindingName="{http://tempuri.org/}CalculatorSoap12" soapVersion="1_2" anonymous="optional" definition="http://www.dneonline.com/calculator.asmx?wsdl" xmlns:xsi="http://www.w3.org/2001/XMLSchema-instance">
    <con:settings id="2b37d146-4aa9-452f-aa13-e89788856a45"/>
    <con:definitionCache type="TEXT" rootPart="http://www.dneonline.com/calculator.asmx?wsdl">
      <con:part>
        <con:url>http://www.dneonline.com/calculator.asmx?wsdl</con:url>
        <con:content><![CDATA[<wsdl:definitions targetNamespace="http://tempuri.org/" xmlns:soap="http://schemas.xmlsoap.org/wsdl/soap/" xmlns:tm="http://microsoft.com/wsdl/mime/textMatching/" xmlns:soapenc="http://schemas.xmlsoap.org/soap/encoding/" xmlns:mime="http://schemas.xmlsoap.org/wsdl/mime/" xmlns:tns="http://tempuri.org/" xmlns:s="http://www.w3.org/2001/XMLSchema" xmlns:soap12="http://schemas.xmlsoap.org/wsdl/soap12/" xmlns:http="http://schemas.xmlsoap.org/wsdl/http/" xmlns:wsdl="http://schemas.xmlsoap.org/wsdl/">
  <wsdl:types>
    <s:schema elementFormDefault="qualified" targetNamespace="http://tempuri.org/">
      <s:element name="Add">
        <s:complexType>
          <s:sequence>
            <s:element minOccurs="1" maxOccurs="1" name="intA" type="s:int"/>
            <s:element minOccurs="1" maxOccurs="1" name="intB" type="s:int"/>
          </s:sequence>
        </s:complexType>
      </s:element>
      <s:element name="AddResponse">
        <s:complexType>
          <s:sequence>
            <s:element minOccurs="1" maxOccurs="1" name="AddResult" type="s:int"/>
          </s:sequence>
        </s:complexType>
      </s:element>
      <s:element name="Subtract">
        <s:complexType>
          <s:sequence>
            <s:element minOccurs="1" maxOccurs="1" name="intA" type="s:int"/>
            <s:element minOccurs="1" maxOccurs="1" name="intB" type="s:int"/>
          </s:sequence>
        </s:complexType>
      </s:element>
      <s:element name="SubtractResponse">
        <s:complexType>
          <s:sequence>
            <s:element minOccurs="1" maxOccurs="1" name="SubtractResult" type="s:int"/>
          </s:sequence>
        </s:complexType>
      </s:element>
      <s:element name="Multiply">
        <s:complexType>
          <s:sequence>
            <s:element minOccurs="1" maxOccurs="1" name="intA" type="s:int"/>
            <s:element minOccurs="1" maxOccurs="1" name="intB" type="s:int"/>
          </s:sequence>
        </s:complexType>
      </s:element>
      <s:element name="MultiplyResponse">
        <s:complexType>
          <s:sequence>
            <s:element minOccurs="1" maxOccurs="1" name="MultiplyResult" type="s:int"/>
          </s:sequence>
        </s:complexType>
      </s:element>
      <s:element name="Divide">
        <s:complexType>
          <s:sequence>
            <s:element minOccurs="1" maxOccurs="1" name="intA" type="s:int"/>
            <s:element minOccurs="1" maxOccurs="1" name="intB" type="s:int"/>
          </s:sequence>
        </s:complexType>
      </s:element>
      <s:element name="DivideResponse">
        <s:complexType>
          <s:sequence>
            <s:element minOccurs="1" maxOccurs="1" name="DivideResult" type="s:int"/>
          </s:sequence>
        </s:complexType>
      </s:element>
    </s:schema>
  </wsdl:types>
  <wsdl:message name="AddSoapIn">
    <wsdl:part name="parameters" element="tns:Add"/>
  </wsdl:message>
  <wsdl:message name="AddSoapOut">
    <wsdl:part name="parameters" element="tns:AddResponse"/>
  </wsdl:message>
  <wsdl:message name="SubtractSoapIn">
    <wsdl:part name="parameters" element="tns:Subtract"/>
  </wsdl:message>
  <wsdl:message name="SubtractSoapOut">
    <wsdl:part name="parameters" element="tns:SubtractResponse"/>
  </wsdl:message>
  <wsdl:message name="MultiplySoapIn">
    <wsdl:part name="parameters" element="tns:Multiply"/>
  </wsdl:message>
  <wsdl:message name="MultiplySoapOut">
    <wsdl:part name="parameters" element="tns:MultiplyResponse"/>
  </wsdl:message>
  <wsdl:message name="DivideSoapIn">
    <wsdl:part name="parameters" element="tns:Divide"/>
  </wsdl:message>
  <wsdl:message name="DivideSoapOut">
    <wsdl:part name="parameters" element="tns:DivideResponse"/>
  </wsdl:message>
  <wsdl:portType name="CalculatorSoap">
    <wsdl:operation name="Add">
      <wsdl:documentation>Adds two integers. This is a test WebService. ©DNE Online</wsdl:documentation>
      <wsdl:input message="tns:AddSoapIn"/>
      <wsdl:output message="tns:AddSoapOut"/>
    </wsdl:operation>
    <wsdl:operation name="Subtract">
      <wsdl:input message="tns:SubtractSoapIn"/>
      <wsdl:output message="tns:SubtractSoapOut"/>
    </wsdl:operation>
    <wsdl:operation name="Multiply">
      <wsdl:input message="tns:MultiplySoapIn"/>
      <wsdl:output message="tns:MultiplySoapOut"/>
    </wsdl:operation>
    <wsdl:operation name="Divide">
      <wsdl:input message="tns:DivideSoapIn"/>
      <wsdl:output message="tns:DivideSoapOut"/>
    </wsdl:operation>
  </wsdl:portType>
  <wsdl:binding name="CalculatorSoap" type="tns:CalculatorSoap">
    <soap:binding transport="http://schemas.xmlsoap.org/soap/http"/>
    <wsdl:operation name="Add">
      <soap:operation soapAction="http://tempuri.org/Add" style="document"/>
      <wsdl:input>
        <soap:body use="literal"/>
      </wsdl:input>
      <wsdl:output>
        <soap:body use="literal"/>
      </wsdl:output>
    </wsdl:operation>
    <wsdl:operation name="Subtract">
      <soap:operation soapAction="http://tempuri.org/Subtract" style="document"/>
      <wsdl:input>
        <soap:body use="literal"/>
      </wsdl:input>
      <wsdl:output>
        <soap:body use="literal"/>
      </wsdl:output>
    </wsdl:operation>
    <wsdl:operation name="Multiply">
      <soap:operation soapAction="http://tempuri.org/Multiply" style="document"/>
      <wsdl:input>
        <soap:body use="literal"/>
      </wsdl:input>
      <wsdl:output>
        <soap:body use="literal"/>
      </wsdl:output>
    </wsdl:operation>
    <wsdl:operation name="Divide">
      <soap:operation soapAction="http://tempuri.org/Divide" style="document"/>
      <wsdl:input>
        <soap:body use="literal"/>
      </wsdl:input>
      <wsdl:output>
        <soap:body use="literal"/>
      </wsdl:output>
    </wsdl:operation>
  </wsdl:binding>
  <wsdl:binding name="CalculatorSoap12" type="tns:CalculatorSoap">
    <soap12:binding transport="http://schemas.xmlsoap.org/soap/http"/>
    <wsdl:operation name="Add">
      <soap12:operation soapAction="http://tempuri.org/Add" style="document"/>
      <wsdl:input>
        <soap12:body use="literal"/>
      </wsdl:input>
      <wsdl:output>
        <soap12:body use="literal"/>
      </wsdl:output>
    </wsdl:operation>
    <wsdl:operation name="Subtract">
      <soap12:operation soapAction="http://tempuri.org/Subtract" style="document"/>
      <wsdl:input>
        <soap12:body use="literal"/>
      </wsdl:input>
      <wsdl:output>
        <soap12:body use="literal"/>
      </wsdl:output>
    </wsdl:operation>
    <wsdl:operation name="Multiply">
      <soap12:operation soapAction="http://tempuri.org/Multiply" style="document"/>
      <wsdl:input>
        <soap12:body use="literal"/>
      </wsdl:input>
      <wsdl:output>
        <soap12:body use="literal"/>
      </wsdl:output>
    </wsdl:operation>
    <wsdl:operation name="Divide">
      <soap12:operation soapAction="http://tempuri.org/Divide" style="document"/>
      <wsdl:input>
        <soap12:body use="literal"/>
      </wsdl:input>
      <wsdl:output>
        <soap12:body use="literal"/>
      </wsdl:output>
    </wsdl:operation>
  </wsdl:binding>
  <wsdl:service name="Calculator">
    <wsdl:port name="CalculatorSoap" binding="tns:CalculatorSoap">
      <soap:address location="http://www.dneonline.com/calculator.asmx"/>
    </wsdl:port>
    <wsdl:port name="CalculatorSoap12" binding="tns:CalculatorSoap12">
      <soap12:address location="http://www.dneonline.com/calculator.asmx"/>
    </wsdl:port>
  </wsdl:service>
</wsdl:definitions>]]></con:content>
        <con:type>http://schemas.xmlsoap.org/wsdl/</con:type>
      </con:part>
    </con:definitionCache>
    <con:endpoints>
      <con:endpoint>http://www.dneonline.com/calculator.asmx</con:endpoint>
    </con:endpoints>
    <con:operation id="ceba0634-b68d-4026-9f1b-22b5cc3126a8" isOneWay="false" action="http://tempuri.org/Add" name="Add" bindingOperationName="Add" type="Request-Response" inputName="" receivesAttachments="false" sendsAttachments="false" anonymous="optional">
      <con:settings/>
      <con:call id="24e65ee9-3e78-4674-afaf-f34922b3a59d" name="Add Request">
        <con:settings/>
        <con:encoding>UTF-8</con:encoding>
        <con:endpoint>http://www.dneonline.com/calculator.asmx</con:endpoint>
        <con:request><![CDATA[<soap:Envelope xmlns:soap="http://www.w3.org/2003/05/soap-envelope" xmlns:tem="http://tempuri.org/">\r
   <soap:Header/>\r
   <soap:Body>\r
      <tem:Add>\r
         <tem:intA>?</tem:intA>\r
         <tem:intB>?</tem:intB>\r
      </tem:Add>\r
   </soap:Body>\r
</soap:Envelope>]]></con:request>
        <con:credentials>
          <con:selectedAuthProfile>No Authorization</con:selectedAuthProfile>
          <con:authType>No Authorization</con:authType>
        </con:credentials>
        <con:jmsConfig JMSDeliveryMode="PERSISTENT"/>
        <con:wsaConfig mustUnderstand="NONE" version="200508" action="http://tempuri.org/CalculatorSoap/AddRequest"/>
        <con:wsrmConfig version="1.2"/>
      </con:call>
    </con:operation>
    <con:operation id="4728f5ae-69b7-48d6-9e72-96dad05e5d29" isOneWay="false" action="http://tempuri.org/Divide" name="Divide" bindingOperationName="Divide" type="Request-Response" inputName="" receivesAttachments="false" sendsAttachments="false" anonymous="optional">
      <con:settings/>
      <con:call id="9f2dff58-bcd7-4ee0-80cc-95a92adc0daf" name="Divide Request">
        <con:settings/>
        <con:encoding>UTF-8</con:encoding>
        <con:endpoint>http://www.dneonline.com/calculator.asmx</con:endpoint>
        <con:request><![CDATA[<soap:Envelope xmlns:soap="http://www.w3.org/2003/05/soap-envelope" xmlns:tem="http://tempuri.org/">\r
   <soap:Header/>\r
   <soap:Body>\r
      <tem:Divide>\r
         <tem:intA>?</tem:intA>\r
         <tem:intB>?</tem:intB>\r
      </tem:Divide>\r
   </soap:Body>\r
</soap:Envelope>]]></con:request>
        <con:credentials>
          <con:selectedAuthProfile>No Authorization</con:selectedAuthProfile>
          <con:authType>No Authorization</con:authType>
        </con:credentials>
        <con:wsaConfig mustUnderstand="NONE" version="200508" action="http://tempuri.org/CalculatorSoap/DivideRequest"/>
      </con:call>
    </con:operation>
    <con:operation id="0dd18e79-9aa7-4929-81fc-2304fc594e29" isOneWay="false" action="http://tempuri.org/Multiply" name="Multiply" bindingOperationName="Multiply" type="Request-Response" inputName="" receivesAttachments="false" sendsAttachments="false" anonymous="optional">
      <con:settings/>
      <con:call id="53570788-7383-4752-8113-2d07ce3f8450" name="Multiply Request">
        <con:settings/>
        <con:encoding>UTF-8</con:encoding>
        <con:endpoint>http://www.dneonline.com/calculator.asmx</con:endpoint>
        <con:request><![CDATA[<soap:Envelope xmlns:soap="http://www.w3.org/2003/05/soap-envelope" xmlns:tem="http://tempuri.org/">\r
   <soap:Header/>\r
   <soap:Body>\r
      <tem:Multiply>\r
         <tem:intA>?</tem:intA>\r
         <tem:intB>?</tem:intB>\r
      </tem:Multiply>\r
   </soap:Body>\r
</soap:Envelope>]]></con:request>
        <con:credentials>
          <con:selectedAuthProfile>No Authorization</con:selectedAuthProfile>
          <con:authType>No Authorization</con:authType>
        </con:credentials>
        <con:wsaConfig mustUnderstand="NONE" version="200508" action="http://tempuri.org/CalculatorSoap/MultiplyRequest"/>
      </con:call>
    </con:operation>
    <con:operation id="b64f7585-3c7b-4ad8-ae8e-cbf85a72493f" isOneWay="false" action="http://tempuri.org/Subtract" name="Subtract" bindingOperationName="Subtract" type="Request-Response" inputName="" receivesAttachments="false" sendsAttachments="false" anonymous="optional">
      <con:settings/>
      <con:call id="9e415548-d85c-496e-acbd-0eedbf8cec2e" name="Subtract Request">
        <con:settings/>
        <con:encoding>UTF-8</con:encoding>
        <con:endpoint>http://www.dneonline.com/calculator.asmx</con:endpoint>
        <con:request><![CDATA[<soap:Envelope xmlns:soap="http://www.w3.org/2003/05/soap-envelope" xmlns:tem="http://tempuri.org/">\r
   <soap:Header/>\r
   <soap:Body>\r
      <tem:Subtract>\r
         <tem:intA>?</tem:intA>\r
         <tem:intB>?</tem:intB>\r
      </tem:Subtract>\r
   </soap:Body>\r
</soap:Envelope>]]></con:request>
        <con:credentials>
          <con:selectedAuthProfile>No Authorization</con:selectedAuthProfile>
          <con:authType>No Authorization</con:authType>
        </con:credentials>
        <con:wsaConfig mustUnderstand="NONE" version="200508" action="http://tempuri.org/CalculatorSoap/SubtractRequest"/>
      </con:call>
    </con:operation>
  </con:interface>
  <con:interface xsi:type="con:RestService" id="345abc71-ae99-4899-8175-9922ddb61faa" wadlVersion="http://wadl.dev.java.net/2009/02" name="http://ipwhois.app" type="rest" xmlns:xsi="http://www.w3.org/2001/XMLSchema-instance">
    <con:settings id="bfa659cf-6496-4b43-9684-5e8216ac42b3"/>
    <con:definitionCache type="TEXT" rootPart=""/>
    <con:endpoints>
      <con:endpoint>http://ipwhois.app</con:endpoint>
    </con:endpoints>
    <con:resource name="IP" path="/json/{IP}" id="9f9ecaa0-b0c1-4361-8dea-f78c33ec8a2d">
      <con:settings/>
      <con:parameters/>
      <con:method name="IP" id="e15fc7b1-30b7-420d-9042-d71dbb4773e8" method="GET">
        <con:settings/>
        <con:parameters>
          <con:parameter required="true">
            <con:name>IP</con:name>
            <con:value>IP</con:value>
            <con:style>TEMPLATE</con:style>
            <con:default>IP</con:default>
            <con:path xsi:nil="true"/>
            <con:description xsi:nil="true"/>
          </con:parameter>
        </con:parameters>
        <con:representation type="RESPONSE">
          <con:mediaType>application/json; charset=utf-8</con:mediaType>
          <con:status>200</con:status>
          <con:params/>
          <con:element xmlns:ip="http://ipwhois.app/json/IP">ip:Response</con:element>
        </con:representation>
        <con:request name="Request 1" id="d14c0d85-af8d-472f-9852-929c9f2cbc29" mediaType="application/json">
          <con:settings/>
          <con:endpoint>http://ipwhois.app</con:endpoint>
          <con:request/>
          <con:credentials>
            <con:selectedAuthProfile>No Authorization</con:selectedAuthProfile>
            <con:authType>No Authorization</con:authType>
          </con:credentials>
          <con:jmsConfig JMSDeliveryMode="PERSISTENT"/>
          <con:parameters>
            <con:entry key="IP" value="IP"/>
          </con:parameters>
          <con:parameterOrder>
            <con:entry>IP</con:entry>
          </con:parameterOrder>
        </con:request>
      </con:method>
    </con:resource>
  </con:interface>
  <con:testSuite id="5eea7be9-74e8-4308-b979-a742b6f0ec88" name="Project 1 Test Suite 1">
    <con:settings id="378493b3-03cd-4f9c-aa52-8b182682299c"/>
    <con:runType>SEQUENTIAL</con:runType>
    <con:testCase id="d72ce7ce-ab7e-47c1-bc4b-ac50d38e2f14" discardOkResults="false" failOnError="false" failTestCaseOnErrors="true" keepSession="false" name="Project 1 Test Case 1" searchProperties="true" timeout="0">
      <con:settings/>
      <con:testStep type="request" id="f06a30b3-a544-4462-bd8d-7a250939d7a3" name="Add Request">
        <con:settings/>
        <con:config xsi:type="con:RequestStep" xmlns:xsi="http://www.w3.org/2001/XMLSchema-instance">
          <con:interface>CalculatorSoap12</con:interface>
          <con:operation>Add</con:operation>
          <con:request name="Add Request" outgoingWss="" incomingWss="" timeout="" sslKeystore="" useWsAddressing="false" useWsReliableMessaging="false" wssPasswordType="" id="32af93f8-b0f2-4a42-8dc2-d1f70bc1950f">
            <con:settings>
              <con:setting id="com.eviware.soapui.impl.wsdl.WsdlRequest@request-headers">&lt;xml-fragment/></con:setting>
            </con:settings>
            <con:encoding>UTF-8</con:encoding>
            <con:endpoint>http://www.dneonline.com/calculator.asmx</con:endpoint>
            <con:request><![CDATA[<soap:Envelope xmlns:soap="http://www.w3.org/2003/05/soap-envelope" xmlns:tem="http://tempuri.org/">\r
   <soap:Header/>\r
   <soap:Body>\r
      <tem:Add>\r
         <tem:intA>10</tem:intA>\r
         <tem:intB>40</tem:intB>\r
      </tem:Add>\r
   </soap:Body>\r
</soap:Envelope>]]></con:request>
            <con:assertion type="SOAP Response" id="31347ae7-abb7-4b22-b3fe-b5f7d72a9485" name="SOAP Response"/>
            <con:assertion type="Valid HTTP Status Codes" id="0eab35ce-cd86-4e59-910e-152afde62255" name="Valid HTTP Status Codes">
              <con:settings/>
              <con:configuration>
                <codes>200</codes>
              </con:configuration>
            </con:assertion>
            <con:assertion type="Schema Compliance" id="ed0e9039-adaf-41d0-859e-633e4ec03c3a" name="Schema Compliance">
              <con:configuration/>
            </con:assertion>
            <con:assertion type="Response SLA Assertion" id="985106d6-6706-464b-a3e1-29cde3b93205" name="Response SLA">
              <con:configuration>
                <SLA>200</SLA>
              </con:configuration>
            </con:assertion>
            <con:assertion type="SOAP Fault Assertion" id="409ef2aa-aa55-4f55-b47e-2a72f9f6581d" name="Not SOAP Fault"/>
            <con:assertion type="XPath Match" id="baf73e94-6c91-48dc-b1f3-8a0e0b193ace" name="XPath Match">
              <con:configuration>
                <path>declare namespace ns1='http://tempuri.org/';
//ns1:AddResponse[1]/ns1:AddResult[1]</path>
                <content>50</content>
                <allowWildcards>false</allowWildcards>
                <ignoreNamspaceDifferences>false</ignoreNamspaceDifferences>
                <ignoreComments>false</ignoreComments>
              </con:configuration>
            </con:assertion>
            <con:credentials>
              <con:selectedAuthProfile>No Authorization</con:selectedAuthProfile>
              <con:authType>No Authorization</con:authType>
            </con:credentials>
            <con:jmsConfig JMSDeliveryMode="PERSISTENT"/>
            <con:wsaConfig mustUnderstand="NONE" version="200508" action="http://tempuri.org/CalculatorSoap/AddRequest"/>
            <con:wsrmConfig version="1.2"/>
          </con:request>
        </con:config>
      </con:testStep>
      <con:testStep type="request" id="611f868f-f225-4d3d-a219-5988e15c9b55" name="Divide Request">
        <con:settings/>
        <con:config xsi:type="con:RequestStep" xmlns:xsi="http://www.w3.org/2001/XMLSchema-instance">
          <con:interface>CalculatorSoap12</con:interface>
          <con:operation>Divide</con:operation>
          <con:request name="Divide Request" outgoingWss="" incomingWss="" timeout="" sslKeystore="" useWsAddressing="false" useWsReliableMessaging="false" wssPasswordType="" id="5bf18780-4297-468d-a048-0de54f1467b5">
            <con:settings/>
            <con:encoding>UTF-8</con:encoding>
            <con:endpoint>http://www.dneonline.com/calculator.asmx</con:endpoint>
            <con:request><![CDATA[<soap:Envelope xmlns:soap="http://www.w3.org/2003/05/soap-envelope" xmlns:tem="http://tempuri.org/">\r
   <soap:Header/>\r
   <soap:Body>\r
      <tem:Divide>\r
         <tem:intA>?</tem:intA>\r
         <tem:intB>?</tem:intB>\r
      </tem:Divide>\r
   </soap:Body>\r
</soap:Envelope>]]></con:request>
            <con:assertion type="SOAP Response" id="a8aa903a-a43a-4a02-adf0-9d4fae79a992" name="SOAP Response"/>
            <con:assertion type="Valid HTTP Status Codes" id="c88b3b13-7a50-41b6-82a0-b715fa33add6" name="Valid HTTP Status Codes">
              <con:settings/>
              <con:configuration>
                <codes>200</codes>
              </con:configuration>
            </con:assertion>
            <con:assertion type="Schema Compliance" id="bde8b942-17ac-4432-af41-6362cf5200ce" name="Schema Compliance">
              <con:configuration/>
            </con:assertion>
            <con:assertion type="Response SLA Assertion" id="f4538a44-0495-4616-bcaf-7ba4a4fb6136" name="Response SLA">
              <con:configuration>
                <SLA>200</SLA>
              </con:configuration>
            </con:assertion>
            <con:assertion type="SOAP Fault Assertion" id="53e55b3a-aede-41b5-8170-158485c07891" name="Not SOAP Fault"/>
            <con:credentials>
              <con:selectedAuthProfile>No Authorization</con:selectedAuthProfile>
              <con:authType>No Authorization</con:authType>
            </con:credentials>
            <con:jmsConfig JMSDeliveryMode="PERSISTENT"/>
            <con:wsaConfig mustUnderstand="NONE" version="200508" action="http://tempuri.org/CalculatorSoap/DivideRequest"/>
          </con:request>
        </con:config>
      </con:testStep>
      <con:testStep type="request" id="ef6fb613-3424-4a70-bc2e-624ac7bb4cbf" name="Multiply Request">
        <con:settings/>
        <con:config xsi:type="con:RequestStep" xmlns:xsi="http://www.w3.org/2001/XMLSchema-instance">
          <con:interface>CalculatorSoap12</con:interface>
          <con:operation>Multiply</con:operation>
          <con:request name="Multiply Request" outgoingWss="" incomingWss="" timeout="" sslKeystore="" useWsAddressing="false" useWsReliableMessaging="false" wssPasswordType="" id="c31a59e6-0f97-4ffa-b8fe-90673754fa61">
            <con:settings/>
            <con:encoding>UTF-8</con:encoding>
            <con:endpoint>http://www.dneonline.com/calculator.asmx</con:endpoint>
            <con:request><![CDATA[<soap:Envelope xmlns:soap="http://www.w3.org/2003/05/soap-envelope" xmlns:tem="http://tempuri.org/">\r
   <soap:Header/>\r
   <soap:Body>\r
      <tem:Multiply>\r
         <tem:intA>?</tem:intA>\r
         <tem:intB>?</tem:intB>\r
      </tem:Multiply>\r
   </soap:Body>\r
</soap:Envelope>]]></con:request>
            <con:assertion type="SOAP Response" id="5276e211-8c87-4e95-9fbe-1018bd7b072a" name="SOAP Response"/>
            <con:assertion type="Valid HTTP Status Codes" id="41d778a2-29b4-4331-8500-c4c0317f6fa9" name="Valid HTTP Status Codes">
              <con:settings/>
              <con:configuration>
                <codes>200</codes>
              </con:configuration>
            </con:assertion>
            <con:assertion type="Schema Compliance" id="f769a20e-8405-4d8a-ba14-c2b9fb8807c1" name="Schema Compliance">
              <con:configuration/>
            </con:assertion>
            <con:assertion type="Response SLA Assertion" id="9db31171-ddd8-4886-a580-b4139b01e0d1" name="Response SLA">
              <con:configuration>
                <SLA>200</SLA>
              </con:configuration>
            </con:assertion>
            <con:assertion type="SOAP Fault Assertion" id="976b0392-5678-4987-be7e-617ed884c44f" name="Not SOAP Fault"/>
            <con:credentials>
              <con:selectedAuthProfile>No Authorization</con:selectedAuthProfile>
              <con:authType>No Authorization</con:authType>
            </con:credentials>
            <con:jmsConfig JMSDeliveryMode="PERSISTENT"/>
            <con:wsaConfig mustUnderstand="NONE" version="200508" action="http://tempuri.org/CalculatorSoap/MultiplyRequest"/>
          </con:request>
        </con:config>
      </con:testStep>
      <con:testStep type="request" id="45b5b316-ca64-45ba-bb0a-07b2b7502792" name="Subtract Request">
        <con:settings/>
        <con:config xsi:type="con:RequestStep" xmlns:xsi="http://www.w3.org/2001/XMLSchema-instance">
          <con:interface>CalculatorSoap12</con:interface>
          <con:operation>Subtract</con:operation>
          <con:request name="Subtract Request" outgoingWss="" incomingWss="" timeout="" sslKeystore="" useWsAddressing="false" useWsReliableMessaging="false" wssPasswordType="" id="f13d19a2-8dbc-4f22-81a1-96e0f625f811">
            <con:settings/>
            <con:encoding>UTF-8</con:encoding>
            <con:endpoint>http://www.dneonline.com/calculator.asmx</con:endpoint>
            <con:request><![CDATA[<soap:Envelope xmlns:soap="http://www.w3.org/2003/05/soap-envelope" xmlns:tem="http://tempuri.org/">\r
   <soap:Header/>\r
   <soap:Body>\r
      <tem:Subtract>\r
         <tem:intA>?</tem:intA>\r
         <tem:intB>?</tem:intB>\r
      </tem:Subtract>\r
   </soap:Body>\r
</soap:Envelope>]]></con:request>
            <con:assertion type="SOAP Response" id="6aeb22bd-9e2f-4d77-996b-9bcd2b65bd02" name="SOAP Response"/>
            <con:assertion type="Valid HTTP Status Codes" id="0ed0cb7b-1945-47a0-a1bc-f069aebdd871" name="Valid HTTP Status Codes">
              <con:settings/>
              <con:configuration>
                <codes>200</codes>
              </con:configuration>
            </con:assertion>
            <con:assertion type="Schema Compliance" id="31063b9c-1b37-42aa-a1d6-142953c7d808" name="Schema Compliance">
              <con:configuration/>
            </con:assertion>
            <con:assertion type="Response SLA Assertion" id="7c21f88f-ba8f-496c-9f6d-b03548c4e051" name="Response SLA">
              <con:configuration>
                <SLA>200</SLA>
              </con:configuration>
            </con:assertion>
            <con:assertion type="SOAP Fault Assertion" id="e7c3d70f-d2f1-48fd-a205-da33e6207d02" name="Not SOAP Fault"/>
            <con:credentials>
              <con:selectedAuthProfile>No Authorization</con:selectedAuthProfile>
              <con:authType>No Authorization</con:authType>
            </con:credentials>
            <con:jmsConfig JMSDeliveryMode="PERSISTENT"/>
            <con:wsaConfig mustUnderstand="NONE" version="200508" action="http://tempuri.org/CalculatorSoap/SubtractRequest"/>
          </con:request>
        </con:config>
      </con:testStep>
      <con:properties/>
      <con:reportParameters/>
    </con:testCase>
    <con:properties/>
    <con:reportParameters/>
  </con:testSuite>
  <con:testSuite id="81fa6fe3-ae6a-45f1-88e7-bea6c14c8791" name="http://ipwhois.app Test Suite">
    <con:settings id="5a40ef7c-366c-4093-bb28-4b0274e3ce9f"/>
    <con:runType>SEQUENTIAL</con:runType>
    <con:testCase id="94a45ce6-3d09-46b3-a72d-d27f22095f8c" discardOkResults="false" failOnError="false" failTestCaseOnErrors="true" keepSession="false" name="http://ipwhois.app Test Case 1" searchProperties="true" timeout="0">
      <con:settings/>
      <con:testStep type="restrequest" name="Request 1" id="fda6264c-4a2d-4495-bd84-4d5f78c3e02e">
        <con:settings/>
        <con:config service="http://ipwhois.app" resourcePath="/json/{IP}" methodName="IP" xsi:type="con:RestRequestStep" xmlns:xsi="http://www.w3.org/2001/XMLSchema-instance">
          <con:restRequest name="Request 1" id="d14c0d85-af8d-472f-9852-929c9f2cbc29" mediaType="application/json">
            <con:settings>
              <con:setting id="com.eviware.soapui.impl.wsdl.WsdlRequest@request-headers">&lt;xml-fragment/></con:setting>
            </con:settings>
            <con:endpoint>http://ipwhois.app</con:endpoint>
            <con:request/>
            <con:originalUri>http://ipwhois.app/json/IP</con:originalUri>
            <con:assertion type="Valid HTTP Status Codes" id="e791d8c3-10b9-474e-8398-9143def88419" name="Valid HTTP Status Codes">
              <con:settings/>
              <con:configuration>
                <codes>200</codes>
              </con:configuration>
            </con:assertion>
            <con:assertion type="JsonPath Match" id="526828e0-0f2f-4feb-abb8-e4477cfe246a" name="JSONPath Match">
              <con:configuration>
                <path>$['country']</path>
                <content>"United States"</content>
                <allowWildcards>false</allowWildcards>
                <ignoreNamspaceDifferences>false</ignoreNamspaceDifferences>
                <ignoreComments>false</ignoreComments>
              </con:configuration>
            </con:assertion>
            <con:credentials>
              <con:selectedAuthProfile>No Authorization</con:selectedAuthProfile>
              <con:authType>No Authorization</con:authType>
            </con:credentials>
            <con:jmsConfig JMSDeliveryMode="PERSISTENT"/>
            <con:parameters>
              <con:entry key="IP" value="IP"/>
            </con:parameters>
            <con:parameterOrder>
              <con:entry>IP</con:entry>
            </con:parameterOrder>
          </con:restRequest>
        </con:config>
      </con:testStep>
      <con:properties/>
      <con:reportParameters/>
    </con:testCase>
    <con:properties/>
    <con:reportParameters/>
  </con:testSuite>
  <con:properties/>
  <con:wssContainer/>
  <con:databaseConnectionContainer/>
  <con:jmsConnectionContainer/>
  <con:oAuth2ProfileContainer/>
  <con:oAuth1ProfileContainer/>
  <con:reporting>
    <con:xmlTemplates/>
    <con:parameters/>
  </con:reporting>
  <con:eventHandlers type="RequestFilter.filterRequest" name="RequestFilter.filterRequest">
    <con:script>// Sample event script to add custom HTTP header to all outgoing REST, SOAP and HTTP(S) calls
// This code is often used for adding custom authentication to ReadyAPI functional tests

// If hardcoding the token, uncomment and change line 5
// token = '4567'

// If your token is parameterized in Project level custom property, uncomment line 8
// token = request.parent.testCase.testSuite.project.getProperty('auth_token').getValue()

// To modify all outgoing calls, remove comments from lines 11 to 16
// headers = request.requestHeaders
// if (headers.containsKey('auth_token2') == false) {
//   headers.put('auth_token2', token)
//   request.requestHeaders = headers
// }</con:script>
  </con:eventHandlers>
  <con:eventHandlers type="TestRunListener.afterStep" name="TestRunListener.afterStep">
    <con:script>// Save all test step results into files
// Change the directory path in line 5 to a location where you want to store details
// then uncomment lines 5 to 10

// filePath = 'C:\\tempOutputDirectory\\'
// fos = new java.io.FileOutputStream(filePath + testStepResult.testStep.label + '.txt', true)
// pw = new java.io.PrintWriter(fos)
// testStepResult.writeTo(pw)
// pw.close()
// fos.close()</con:script>
  </con:eventHandlers>
  <con:authRepository/>
  <con:tags/>
</con:soapui-project>
